{
  "key": "tangle-004",
  "title": "Tangle 4 - Setup GitHub, Docker",
  "author": "teefal",
  "postStamp": "2023-11-28 06:00:00",
  "thumb": "https://i.ytimg.com/vi/pQRPuhWny8c/hqdefault.jpg?sqp=-oaymwEcCNACELwBSFXyq4qpAw4IARUAAIhCGAFwAcABBg==&rs=AOn4CLC3SC2Jt89QFDvYmEQ-uqbLjAJvTg",
  "body": "Both causing revolutions in software development, GitHub greatly expanded the reach of open source and Docker popularized portable containers. Tim creates and configures both accounts.",
  "youtube": "https://youtu.be/pQRPuhWny8c"
}